cstructpy/__init__.py
cstructpy/data_models.py
cstructpy/exceptions.py
cstructpy/primitives.py
cstructpy-0.2.2.dist-info/LICENSE
cstructpy-0.2.2.dist-info/METADATA
cstructpy-0.2.2.dist-info/WHEEL
cstructpy-0.2.2.dist-info/top_level.txt
cstructpy-0.2.2.dist-info/RECORD
