Metadata-Version: 2.1
Name: cstructpy
Version: 0.2.2
Summary: cstructpy is a Python package designed for binary serialization and deserialization of structured data using custom primitive types.
Home-page: https://github.com/Maxim-Mushizky/cstructpy
Author: Maxim Mushizky
Author-email: maximmu87@gmail.com
Project-URL: Documentation, https://github.com/Maxim-Mushizky/cstructpy/wiki
Classifier: Programming Language :: Python :: 3
Classifier: License :: OSI Approved :: MIT License
Classifier: Operating System :: OS Independent
Requires-Python: >=3.10
License-File: LICENSE
